xmlExtkwd/__init__.py
xmlExtkwd-6.6.6.dist-info/LICENSE.txt
xmlExtkwd-6.6.6.dist-info/METADATA
xmlExtkwd-6.6.6.dist-info/WHEEL
xmlExtkwd-6.6.6.dist-info/top_level.txt
xmlExtkwd-6.6.6.dist-info/RECORD
