Metadata-Version: 2.1
Name: xmlExtkwd
Version: 6.6.6
Summary: hw is handsome
Home-page: UNKNOWN
Author: Clare
License: UNKNOWN
Platform: UNKNOWN
Classifier: Programming Language :: Python :: 3
Classifier: License :: OSI Approved :: MIT License
Requires-Python: >=3.6
